gradle.properties
hexdoc_hexresearch/__gradle_version__.py
hexdoc_hexresearch/__init__.py
hexdoc_hexresearch/__version__.py
hexdoc_hexresearch/_hooks.py
hexdoc_hexresearch/py.typed
hexdoc_hexresearch/_export/.gitignore
hexdoc_hexresearch/_export/__init__.py
hexdoc_hexresearch/_export/generated/__init__.py
hexdoc_hexresearch/_export/generated/hexresearch.hexdoc.json
hexdoc_hexresearch/_export/generated/hexresearch.patterns.hexdoc.json
hexdoc_hexresearch/_export/generated/assets/hexcasting/lang/en_us.flatten.json5
hexdoc_hexresearch/_export/generated/assets/hexresearch/blockstates/cognitive_inducer.json
hexdoc_hexresearch/_export/generated/assets/hexresearch/lang/en_us.json
hexdoc_hexresearch/_export/generated/assets/hexresearch/lang/zh_cn.json
hexdoc_hexresearch/_export/generated/assets/hexresearch/models/block/cognitive_inducer.json
hexdoc_hexresearch/_export/generated/assets/hexresearch/models/item/cognitive_inducer.json
hexdoc_hexresearch/_export/generated/assets/hexresearch/textures/mob_effect/mind_fatigue.png
hexdoc_hexresearch/_export/generated/data/hexdoc/tags/advancements/spoilered.json
hexdoc_hexresearch/_export/generated/data/hexresearch/patchouli_books/hexresearchbook/book.json
hexdoc_hexresearch/_export/generated/data/hexresearch/patchouli_books/hexresearchbook/en_us/entries/greatwork/enlightened_thought_sieve.json
hexdoc_hexresearch/_export/generated/data/hexresearch/patchouli_books/hexresearchbook/en_us/entries/items/cognitive_inducer.json
hexdoc_hexresearch/_export/generated/data/hexresearch/patchouli_books/hexresearchbook/en_us/entries/patterns/villager_actions.json
hexdoc_hexresearch/_export/generated/data/hexresearch/patchouli_books/hexresearchbook/en_us/entries/patterns/great_spells/imbue_mind.json
hexdoc_hexresearch/_export/generated/data/hexresearch/patchouli_books/hexresearchbook/en_us/entries/patterns/spells/thought_sieve.json
hexdoc_hexresearch/_export/generated/data/hexresearch/recipes/cognitive_inducer.json
hexdoc_hexresearch-1.0.1.1.0.dev0.dist-info/METADATA
hexdoc_hexresearch-1.0.1.1.0.dev0.dist-info/WHEEL
hexdoc_hexresearch-1.0.1.1.0.dev0.dist-info/entry_points.txt
hexdoc_hexresearch-1.0.1.1.0.dev0.dist-info/licenses/LICENSE.txt
hexdoc_hexresearch-1.0.1.1.0.dev0.dist-info/RECORD
