Metadata-Version: 2.1
Name: hexdoc-hexresearch
Version: 1.0.1.1.0.dev0
Summary: Python web book docgen and hexdoc plugin for Hex Research.
Project-URL: Homepage, https://dashkal.github.io/hexresearch
Project-URL: Source, https://github.com/Dashkal/hexresearch
Author: Dashkal
License-File: LICENSE.txt
Keywords: hexdoc
Requires-Python: >=3.11
Requires-Dist: hexdoc-hexcasting~=0.10.3.1.0.dev20
Provides-Extra: dev
Requires-Dist: ruff~=0.1.4; extra == 'dev'
